help_desk_client/__init__.py
help_desk_client/interfaces.py
help_desk_client/zendesk_manager.py
help_desk_client-0.2.0.dist-info/LICENSE.txt
help_desk_client-0.2.0.dist-info/WHEEL
help_desk_client-0.2.0.dist-info/METADATA
help_desk_client-0.2.0.dist-info/RECORD
